rest_framework_proxy/__init__.py
rest_framework_proxy/adapters.py
rest_framework_proxy/models.py
rest_framework_proxy/settings.py
rest_framework_proxy/utils.py
rest_framework_proxy/views.py
django_rest_framework_proxy_iara-1.6.0.dist-info/METADATA
django_rest_framework_proxy_iara-1.6.0.dist-info/WHEEL
django_rest_framework_proxy_iara-1.6.0.dist-info/top_level.txt
django_rest_framework_proxy_iara-1.6.0.dist-info/RECORD
